LICENSE
MANIFEST.in
README.rst
setup.py
leftronicd/__init__.py
leftronicd/constants.py
leftronicd/helpers.py
leftronicd/main.py
leftronicd/contrib/__init__.py
leftronicd/contrib/dbretriever.py
leftronicd/contrib/database/__init__.py
leftronicd/contrib/database/databaseRetriever.py
leftronicd_db.egg-info/PKG-INFO
leftronicd_db.egg-info/SOURCES.txt
leftronicd_db.egg-info/dependency_links.txt
leftronicd_db.egg-info/entry_points.txt
leftronicd_db.egg-info/requires.txt
leftronicd_db.egg-info/top_level.txt