Metadata-Version: 1.0
Name: leftronicd-db
Version: 0.1
Summary: A twisted based daemon to send metrics to leftronic.com
Home-page: https://github.com/sonofabell/leftronicd
Author: Jonas Obrist, Henry Barnor
Author-email: ojiidotch@gmail.com, henry@leftronic.com
License: BSD
Platform: OS Independent
